shows/__init__.py
shows/component.py
shows/core.py
shows/main.py
shows-0.0.1.dist-info/LICENSE
shows-0.0.1.dist-info/METADATA
shows-0.0.1.dist-info/WHEEL
shows-0.0.1.dist-info/entry_points.txt
shows-0.0.1.dist-info/top_level.txt
shows-0.0.1.dist-info/RECORD
