Metadata-Version: 2.1
Name: shows
Version: 0.0.1
Summary: UNKNOWN
Home-page: https://github.com/voidful/shows
Author: Voidful
Author-email: voidful.stack@gmail.com
License: Apache
Keywords: system monitoring gpu cpu network memory disk utility usage state
Platform: UNKNOWN
Classifier: Development Status :: 4 - Beta
Classifier: Intended Audience :: End Users/Desktop
Classifier: Topic :: System :: Monitoring
Classifier: License :: OSI Approved :: Apache Software License
Classifier: Programming Language :: Python
Requires-Dist: unidecode
Requires-Dist: py-cpuinfo
Requires-Dist: gpustat
Requires-Dist: psutil
Requires-Dist: rich
